qodo/__init__.py
qodo/main.py
qodo/auth/__init__.py
qodo/auth/auth_jwt.py
qodo/auth/deps.py
qodo/auth/deps_employes.py
qodo/conf/__init__.py
qodo/conf/database.py
qodo/conf/logging_config.py
qodo/conf/session_config.py
qodo/controllers/__init__.py
qodo/controllers/report_controller.py
qodo/controllers/payments/pix.py
qodo/controllers/payments/partial/__init__.py
qodo/controllers/payments/partial/create_depts.py
qodo/controllers/payments/partial/process_partial_payments.py
qodo/controllers/payments/partial/update_depts.py
qodo/controllers/payments/partial/views_depts.py
qodo/controllers/products/__init__.py
qodo/controllers/products/monitoring_products.py
qodo/controllers/products/products_infors.py
qodo/controllers/user/___init__.py
qodo/controllers/user/create_account.py
qodo/controllers/user/system_users.py
qodo/core/__init__.py
qodo/core/cache.py
qodo/core/session_manager.py
qodo/logs/__init__.py
qodo/logs/infos.py
qodo/model/__init__.py
qodo/model/caixa.py
qodo/model/carItems.py
qodo/model/cashmovement.py
qodo/model/cnpjCache.py
qodo/model/customers.py
qodo/model/delivery.py
qodo/model/employee.py
qodo/model/fornecedor.py
qodo/model/membros.py
qodo/model/partial.py
qodo/model/pix.py
qodo/model/product.py
qodo/model/sale.py
qodo/model/tickets.py
qodo/model/user.py
qodo/routes/__init__.py
qodo/routes/cliente_cnpj.py
qodo/routes/login.py
qodo/routes/registre.py
qodo/routes/updates.py
qodo/routes/account/__init__.py
qodo/routes/account/account.py
qodo/routes/account/employee_edit.py
qodo/routes/account/employee_list.py
qodo/routes/caixa/__init__.py
qodo/routes/caixa/box_closing.py
qodo/routes/caixa/checkout_report.py
qodo/routes/caixa/informations.py
qodo/routes/caixa/login.py
qodo/routes/caixa/start_router.py
qodo/routes/caixa/status.py
qodo/routes/caixa/summary.py
qodo/routes/car/__init__.py
qodo/routes/car/adjustments.py
qodo/routes/car/create.py
qodo/routes/car/delete.py
qodo/routes/car/list.py
qodo/routes/car/paymente_partial.py
qodo/routes/car/pdv.py
qodo-0.1.0.dist-info/METADATA
qodo-0.1.0.dist-info/WHEEL
qodo-0.1.0.dist-info/entry_points.txt
qodo-0.1.0.dist-info/top_level.txt
qodo-0.1.0.dist-info/RECORD
