Metadata-Version: 2.4
Name: qodo
Version: 0.1.0
Summary: Sistema completo de PDV (Ponto de Venda) com múltiplos recursos e integrações
Home-page: https://github.com/Gilderlan0101/qodo-pdv
Author: Qodo Tech
Author-email: dacruzgg01@gmail.com
Project-URL: Documentation, https://github.com/Gilderlan0101/qodo-pdv
Project-URL: Source, https://github.com/Gilderlan0101/qodo-pdv
Project-URL: Tracker, https://github.com/Gilderlan0101/qodo-pdv/issues
Keywords: pdv ponto-de-venda venda checkout fastapi sqlite mysql
Classifier: Development Status :: 4 - Beta
Classifier: Intended Audience :: Developers
Classifier: Intended Audience :: Financial and Insurance Industry
Classifier: Intended Audience :: End Users/Desktop
Classifier: Topic :: Office/Business :: Financial :: Point-Of-Sale
Classifier: License :: OSI Approved :: MIT License
Classifier: Programming Language :: Python :: 3
Classifier: Programming Language :: Python :: 3.8
Classifier: Programming Language :: Python :: 3.9
Classifier: Programming Language :: Python :: 3.10
Classifier: Programming Language :: Python :: 3.11
Classifier: Programming Language :: Python :: 3.12
Requires-Python: >=3.8
Requires-Dist: fastapi
Requires-Dist: uvicorn
Requires-Dist: sqlmodel
Requires-Dist: pydantic
Requires-Dist: pydantic-settings
Requires-Dist: python-dotenv
Requires-Dist: python-jose
Requires-Dist: passlib
Requires-Dist: httpx
Requires-Dist: email-validator
Requires-Dist: faker
Requires-Dist: aiomysql
Requires-Dist: bcrypt==4.3.0
Requires-Dist: tortoise-orm
Requires-Dist: redis
Requires-Dist: requests
Requires-Dist: fpdf
Requires-Dist: jose
Requires-Dist: python-multipart
Requires-Dist: validate_docbr
Requires-Dist: pydantic_br
Provides-Extra: dev
Requires-Dist: pytest>=7.0.0; extra == "dev"
Requires-Dist: black>=22.0.0; extra == "dev"
Requires-Dist: flake8>=4.0.0; extra == "dev"
Requires-Dist: mypy>=1.0.0; extra == "dev"
Provides-Extra: mysql
Requires-Dist: aiomysql>=0.2.0; extra == "mysql"
Requires-Dist: pymysql>=1.0.0; extra == "mysql"
Provides-Extra: sqlite
Requires-Dist: aiosqlite>=0.18.0; extra == "sqlite"
Dynamic: author
Dynamic: author-email
Dynamic: classifier
Dynamic: description
Dynamic: description-content-type
Dynamic: home-page
Dynamic: keywords
Dynamic: project-url
Dynamic: provides-extra
Dynamic: requires-dist
Dynamic: requires-python
Dynamic: summary
